pilot/VERSION
pilot/__init__.py
pilot/arguments.py
pilot/build.py
pilot/configdefs.json
pilot/device.py
pilot/helper.py
pilot/init.py
pilot/main.py
pilot/modulehelp.py
pilot/moduleinfo.py
pilot/pilot.py
pilot/pilotdriver.py
pilot/pilotserver.py
pilot/pilotsetup.py
pilot/plc.py
pilot/program.py
pilot/project.py
pilot/remote.py
pilot/remoteit.py
pilot/reset.py
pilot/sbc.py
pilot/server.py
pilot/targethardware.json
pilot/test.py
pilot/bin/arm32/jamplayer
pilot/bin/arm32/stm32flash
pilot/bin/arm64/jamplayer
pilot/bin/arm64/stm32flash
pilot/bin/cortex-a53_32bit/jamplayer
pilot/bin/cortex-a53_32bit/stm32flash
pilot/bin/cortex-a53_64bit/jamplayer
pilot/bin/cortex-a53_64bit/stm32flash
pilot/compiler/_iec61131-3/__init__.py
pilot/compiler/_iec61131-3/compiler.py
pilot/compiler/_iec61131-3/template.yml
pilot/compiler/_iec61131-3/matiec/linux/iec2c
pilot/compiler/_iec61131-3/matiec/linux/lib/COPYING.LESSER
pilot/compiler/_iec61131-3/matiec/linux/lib/bistable.txt
pilot/compiler/_iec61131-3/matiec/linux/lib/counter.txt
pilot/compiler/_iec61131-3/matiec/linux/lib/create_standard_function_txt.sh
pilot/compiler/_iec61131-3/matiec/linux/lib/derivative_st.txt
pilot/compiler/_iec61131-3/matiec/linux/lib/edge_detection.txt
pilot/compiler/_iec61131-3/matiec/linux/lib/hysteresis_st.txt
pilot/compiler/_iec61131-3/matiec/linux/lib/ieclib.txt
pilot/compiler/_iec61131-3/matiec/linux/lib/integral_st.txt
pilot/compiler/_iec61131-3/matiec/linux/lib/pid_st.txt
pilot/compiler/_iec61131-3/matiec/linux/lib/ramp_st.txt
pilot/compiler/_iec61131-3/matiec/linux/lib/rtc.txt
pilot/compiler/_iec61131-3/matiec/linux/lib/sema.txt
pilot/compiler/_iec61131-3/matiec/linux/lib/standard_FB.txt
pilot/compiler/_iec61131-3/matiec/linux/lib/standard_functions.txt
pilot/compiler/_iec61131-3/matiec/linux/lib/test_iec_std_lib.c
pilot/compiler/_iec61131-3/matiec/linux/lib/timer.txt
pilot/compiler/_iec61131-3/matiec/linux/lib/C/accessor.h
pilot/compiler/_iec61131-3/matiec/linux/lib/C/iec_std_FB.h
pilot_config-2.5.14.dist-info/LICENSE.txt
pilot_config-2.5.14.dist-info/METADATA
pilot_config-2.5.14.dist-info/WHEEL
pilot_config-2.5.14.dist-info/entry_points.txt
pilot_config-2.5.14.dist-info/top_level.txt
pilot_config-2.5.14.dist-info/RECORD
